{
	"song": {
		"player1": "saberbf",
		"bfTrails": false,
		"notes": [
			{
				"sectionBeats": 4,
				"sectionNotes": [
					[
						80,
						2,
						0
					],
					[
						560,
						2,
						0
					],
					[
						560,
						3,
						0
					],
					[
						1040,
						2,
						0
					],
					[
						1040,
						3,
						0
					],
					[
						1520,
						2,
						0
					],
					[
						1520,
						3,
						0
					],
					[
						1760,
						1,
						0
					],
					[
						320,
						1,
						0,
						"Bomb Note"
					],
					[
						800,
						1,
						0,
						"Bomb Note"
					],
					[
						1280,
						1,
						0,
						"Bomb Note"
					],
					[
						80,
						3,
						0
					],
					[
						0,
						7,
						0
					]
				],
				"typeOfSection": 0,
				"gfSection": false,
				"altAnim": false,
				"mustHitSection": true,
				"changeBPM": false,
				"bpm": 150
			},
			{
				"sectionBeats": 4,
				"sectionNotes": [
					[
						2000,
						2,
						0
					],
					[
						2000,
						3,
						0
					],
					[
						2480,
						2,
						0
					],
					[
						2480,
						3,
						0
					],
					[
						2960,
						2,
						0
					],
					[
						2960,
						3,
						0
					],
					[
						3440,
						2,
						0
					],
					[
						3440,
						3,
						0
					],
					[
						3680,
						0,
						0
					],
					[
						2240,
						1,
						0,
						"Bomb Note"
					],
					[
						2720,
						0,
						0,
						"Bomb Note"
					],
					[
						3200,
						0,
						0,
						"Bomb Note"
					]
				],
				"typeOfSection": 0,
				"gfSection": false,
				"altAnim": false,
				"mustHitSection": true,
				"changeBPM": false,
				"bpm": 150
			},
			{
				"sectionBeats": 4,
				"sectionNotes": [
					[
						4400,
						2,
						0
					],
					[
						4400,
						3,
						0
					],
					[
						4880,
						2,
						0
					],
					[
						4880,
						3,
						0
					],
					[
						5360,
						2,
						0
					],
					[
						5360,
						3,
						0
					],
					[
						5600,
						1,
						0
					],
					[
						3920,
						2,
						0
					],
					[
						3920,
						3,
						0
					],
					[
						4000,
						0,
						0,
						"Bomb Note"
					],
					[
						4640,
						1,
						0,
						"Bomb Note"
					],
					[
						5120,
						1,
						0,
						"Bomb Note"
					]
				],
				"typeOfSection": 0,
				"gfSection": false,
				"altAnim": false,
				"mustHitSection": true,
				"changeBPM": false,
				"bpm": 125
			},
			{
				"sectionBeats": 4,
				"sectionNotes": [
					[
						5840,
						2,
						0
					],
					[
						5840,
						3,
						0
					],
					[
						6320,
						1,
						0
					],
					[
						6320,
						0,
						0
					],
					[
						7520,
						0,
						0
					],
					[
						7280,
						1,
						0
					],
					[
						7520,
						1,
						0
					],
					[
						6800,
						1,
						0
					],
					[
						6800,
						0,
						0
					],
					[
						6080,
						1,
						0,
						"Bomb Note"
					],
					[
						6560,
						3,
						0,
						"Bomb Note"
					],
					[
						7040,
						3,
						0,
						"Bomb Note"
					]
				],
				"typeOfSection": 0,
				"gfSection": false,
				"altAnim": false,
				"mustHitSection": true,
				"changeBPM": false,
				"bpm": 125
			},
			{
				"sectionBeats": 4,
				"sectionNotes": [
					[
						8240,
						2,
						0
					],
					[
						8240,
						3,
						0
					],
					[
						8720,
						2,
						0
					],
					[
						8720,
						3,
						0
					],
					[
						9200,
						2,
						0
					],
					[
						9200,
						3,
						0
					],
					[
						9440,
						1,
						0
					],
					[
						7760,
						1,
						0
					],
					[
						7760,
						0,
						0
					],
					[
						8000,
						1,
						0,
						"Bomb Note"
					],
					[
						8480,
						1,
						0,
						"Bomb Note"
					],
					[
						8960,
						1,
						0,
						"Bomb Note"
					]
				],
				"typeOfSection": 0,
				"gfSection": false,
				"altAnim": false,
				"mustHitSection": true,
				"changeBPM": false,
				"bpm": 125
			},
			{
				"sectionBeats": 4,
				"sectionNotes": [
					[
						9680,
						2,
						0
					],
					[
						9680,
						3,
						0
					],
					[
						10160,
						2,
						0
					],
					[
						10160,
						3,
						0
					],
					[
						10640,
						2,
						0
					],
					[
						10640,
						3,
						0
					],
					[
						11120,
						2,
						0
					],
					[
						11120,
						3,
						0
					],
					[
						11360,
						0,
						0
					],
					[
						9920,
						1,
						0,
						"Bomb Note"
					],
					[
						10400,
						0,
						0,
						"Bomb Note"
					],
					[
						10880,
						0,
						0,
						"Bomb Note"
					]
				],
				"typeOfSection": 0,
				"gfSection": false,
				"altAnim": false,
				"mustHitSection": true,
				"changeBPM": false,
				"bpm": 125
			},
			{
				"sectionBeats": 4,
				"sectionNotes": [
					[
						12080,
						2,
						0
					],
					[
						12080,
						3,
						0
					],
					[
						12560,
						2,
						0
					],
					[
						12560,
						3,
						0
					],
					[
						13040,
						2,
						0
					],
					[
						13040,
						3,
						0
					],
					[
						13280,
						1,
						0
					],
					[
						11600,
						2,
						0
					],
					[
						11600,
						3,
						0
					],
					[
						11840,
						0,
						0,
						"Bomb Note"
					],
					[
						12320,
						1,
						0,
						"Bomb Note"
					],
					[
						12800,
						1,
						0,
						"Bomb Note"
					]
				],
				"typeOfSection": 0,
				"gfSection": false,
				"altAnim": false,
				"mustHitSection": true,
				"changeBPM": false,
				"bpm": 125
			},
			{
				"sectionBeats": 4,
				"sectionNotes": [
					[
						13520,
						2,
						0
					],
					[
						13520,
						3,
						0
					],
					[
						14000,
						1,
						0
					],
					[
						14000,
						0,
						0
					],
					[
						15200,
						0,
						0
					],
					[
						14960,
						1,
						0
					],
					[
						15200,
						1,
						0
					],
					[
						14480,
						1,
						0
					],
					[
						14480,
						0,
						0
					],
					[
						13760,
						1,
						0,
						"Bomb Note"
					],
					[
						14240,
						3,
						0,
						"Bomb Note"
					],
					[
						14720,
						3,
						0,
						"Bomb Note"
					]
				],
				"typeOfSection": 0,
				"gfSection": false,
				"altAnim": false,
				"mustHitSection": true,
				"changeBPM": false,
				"bpm": 125
			},
			{
				"sectionBeats": 4,
				"sectionNotes": [
					[
						15920,
						2,
						0
					],
					[
						15920,
						0,
						0
					],
					[
						16400,
						2,
						0
					],
					[
						16960,
						1,
						0
					],
					[
						16720,
						2,
						0
					],
					[
						17240,
						1,
						0
					],
					[
						15440,
						1,
						0
					],
					[
						15440,
						0,
						0
					],
					[
						15680,
						1,
						0,
						"Bomb Note"
					],
					[
						16160,
						0,
						0,
						"Bomb Note"
					],
					[
						16160,
						1,
						0,
						"Bomb Note"
					],
					[
						16160,
						2,
						0,
						"Bomb Note"
					]
				],
				"typeOfSection": 0,
				"gfSection": false,
				"altAnim": false,
				"mustHitSection": true,
				"changeBPM": false,
				"bpm": 125
			},
			{
				"sectionBeats": 4,
				"sectionNotes": [
					[
						17360,
						3,
						0
					],
					[
						17360,
						2,
						0
					],
					[
						17840,
						1,
						0
					],
					[
						18320,
						1,
						0
					],
					[
						18640,
						2,
						0
					],
					[
						19040,
						2,
						0
					],
					[
						18080,
						1,
						0,
						"Bomb Note"
					],
					[
						18080,
						2,
						0,
						"Bomb Note"
					],
					[
						18080,
						3,
						0,
						"Bomb Note"
					],
					[
						17600,
						1,
						0,
						"Bomb Note"
					],
					[
						17600,
						0,
						0,
						"Bomb Note"
					],
					[
						17840,
						0,
						0
					]
				],
				"typeOfSection": 0,
				"gfSection": false,
				"altAnim": false,
				"mustHitSection": true,
				"changeBPM": false,
				"bpm": 125
			},
			{
				"sectionBeats": 4,
				"sectionNotes": [
					[
						19280,
						1,
						0
					],
					[
						19280,
						3,
						0
					],
					[
						19520,
						2,
						0
					],
					[
						19760,
						2,
						0
					],
					[
						19760,
						0,
						0
					],
					[
						20240,
						2,
						0
					],
					[
						20800,
						1,
						0
					],
					[
						21080,
						1,
						0
					],
					[
						20000,
						1,
						0,
						"Bomb Note"
					],
					[
						20000,
						0,
						0,
						"Bomb Note"
					],
					[
						20000,
						2,
						0,
						"Bomb Note"
					],
					[
						20560,
						1,
						0
					]
				],
				"typeOfSection": 0,
				"gfSection": false,
				"altAnim": false,
				"mustHitSection": true,
				"changeBPM": false,
				"bpm": 125
			},
			{
				"sectionBeats": 4,
				"sectionNotes": [
					[
						21200,
						3,
						0
					],
					[
						21200,
						2,
						0
					],
					[
						21680,
						2,
						0
					],
					[
						21680,
						0,
						0
					],
					[
						22480,
						2,
						0
					],
					[
						22160,
						0,
						0
					],
					[
						22880,
						0,
						0
					],
					[
						21440,
						3,
						0,
						"Bomb Note"
					],
					[
						21440,
						0,
						0,
						"Bomb Note"
					],
					[
						21920,
						2,
						0,
						"Bomb Note"
					],
					[
						21920,
						3,
						0,
						"Bomb Note"
					],
					[
						21920,
						1,
						0,
						"Bomb Note"
					],
					[
						22720,
						3,
						0,
						"Bomb Note"
					],
					[
						22720,
						1,
						0,
						"Bomb Note"
					]
				],
				"typeOfSection": 0,
				"gfSection": false,
				"altAnim": false,
				"mustHitSection": true,
				"changeBPM": false,
				"bpm": 125
			},
			{
				"sectionBeats": 4,
				"sectionNotes": [
					[
						23120,
						1,
						0
					],
					[
						23120,
						3,
						0
					],
					[
						23360,
						2,
						0
					],
					[
						23600,
						0,
						0
					],
					[
						24080,
						2,
						0
					],
					[
						24400,
						2,
						0
					],
					[
						24640,
						0,
						0
					],
					[
						23720,
						1,
						0
					],
					[
						23840,
						0,
						0
					],
					[
						23960,
						1,
						0
					],
					[
						24200,
						1,
						0
					],
					[
						24280,
						3,
						0
					],
					[
						24520,
						3,
						0
					],
					[
						24760,
						3,
						0
					],
					[
						24880,
						1,
						0
					]
				],
				"typeOfSection": 0,
				"gfSection": false,
				"altAnim": false,
				"mustHitSection": true,
				"changeBPM": false,
				"bpm": 125
			},
			{
				"sectionBeats": 4,
				"sectionNotes": [
					[
						25040,
						3,
						0
					],
					[
						25040,
						2,
						0
					],
					[
						25520,
						0,
						0
					],
					[
						26320,
						2,
						0
					],
					[
						26000,
						0,
						0
					],
					[
						26720,
						2,
						0
					],
					[
						26720,
						0,
						0
					],
					[
						25640,
						3,
						0
					],
					[
						25760,
						2,
						0
					],
					[
						25880,
						1,
						0
					],
					[
						26200,
						0,
						0
					],
					[
						25280,
						0,
						0,
						"Bomb Note"
					],
					[
						25280,
						1,
						0,
						"Bomb Note"
					],
					[
						25280,
						3,
						0,
						"Bomb Note"
					],
					[
						25280,
						2,
						0,
						"Bomb Note"
					],
					[
						26560,
						1,
						0,
						"Bomb Note"
					],
					[
						26560,
						3,
						0,
						"Bomb Note"
					],
					[
						26120,
						2,
						0
					]
				],
				"typeOfSection": 0,
				"gfSection": false,
				"altAnim": false,
				"mustHitSection": true,
				"changeBPM": false,
				"bpm": 125
			},
			{
				"sectionBeats": 4,
				"sectionNotes": [
					[
						27200,
						1,
						0
					],
					[
						26960,
						1,
						0
					],
					[
						26960,
						3,
						0
					],
					[
						27200,
						2,
						0
					],
					[
						27440,
						2,
						0
					],
					[
						27440,
						0,
						0
					],
					[
						27680,
						2,
						0
					],
					[
						27560,
						1,
						0
					],
					[
						27800,
						1,
						0
					],
					[
						27920,
						2,
						0
					],
					[
						28040,
						1,
						0
					],
					[
						28160,
						2,
						0
					],
					[
						28280,
						1,
						0
					],
					[
						28400,
						2,
						0
					],
					[
						28520,
						1,
						0
					],
					[
						28640,
						2,
						0
					],
					[
						28760,
						1,
						0
					]
				],
				"typeOfSection": 0,
				"gfSection": false,
				"altAnim": false,
				"mustHitSection": true,
				"changeBPM": false,
				"bpm": 125
			},
			{
				"sectionBeats": 4,
				"sectionNotes": [
					[
						28880,
						2,
						0
					],
					[
						29000,
						1,
						0
					],
					[
						29120,
						2,
						0
					],
					[
						29240,
						1,
						0
					],
					[
						29400,
						1,
						0
					],
					[
						29680,
						1,
						0
					],
					[
						29840,
						0,
						0
					],
					[
						30080,
						1,
						0
					],
					[
						29840,
						2,
						0
					],
					[
						30320,
						1,
						0
					],
					[
						30320,
						3,
						0
					],
					[
						30640,
						1,
						0
					],
					[
						29600,
						2,
						0
					],
					[
						30160,
						2,
						0
					],
					[
						30560,
						2,
						0
					]
				],
				"typeOfSection": 0,
				"gfSection": false,
				"altAnim": false,
				"mustHitSection": true,
				"changeBPM": false,
				"bpm": 125
			},
			{
				"sectionBeats": 4,
				"sectionNotes": [
					[
						30800,
						2,
						0
					],
					[
						30800,
						0,
						360
					],
					[
						32106.6666666667,
						3,
						0
					],
					[
						31520,
						2,
						0
					],
					[
						31760,
						1,
						0
					],
					[
						32000,
						1,
						0
					],
					[
						31040,
						1,
						0,
						"Bomb Note"
					],
					[
						31040,
						2,
						0,
						"Bomb Note"
					],
					[
						32240,
						0,
						240,
						"Wall Note"
					],
					[
						31280,
						1,
						0
					],
					[
						31520,
						0,
						0
					],
					[
						32400,
						3,
						0
					],
					[
						32480,
						2,
						0
					]
				],
				"typeOfSection": 0,
				"gfSection": false,
				"altAnim": false,
				"mustHitSection": true,
				"changeBPM": false,
				"bpm": 125
			},
			{
				"sectionBeats": 4,
				"sectionNotes": [
					[
						34026.6666666667,
						3,
						0
					],
					[
						33920,
						1,
						0
					],
					[
						34320,
						3,
						0
					],
					[
						32720,
						1,
						0
					],
					[
						33080,
						1,
						0
					],
					[
						32960,
						0,
						0
					],
					[
						33320,
						1,
						0
					],
					[
						33440,
						0,
						0
					],
					[
						33680,
						2,
						0
					],
					[
						32720,
						3,
						1080,
						"Wall Note"
					],
					[
						34160,
						0,
						480,
						"Wall Note"
					]
				],
				"typeOfSection": 0,
				"gfSection": false,
				"altAnim": false,
				"mustHitSection": true,
				"changeBPM": false,
				"bpm": 125
			},
			{
				"sectionBeats": 4,
				"sectionNotes": [
					[
						35946.6666666667,
						3,
						0
					],
					[
						35360,
						2,
						0
					],
					[
						35600,
						1,
						0
					],
					[
						35840,
						1,
						0
					],
					[
						36080,
						0,
						240,
						"Wall Note"
					],
					[
						35360,
						0,
						0
					],
					[
						36240,
						3,
						0
					],
					[
						36320,
						2,
						0
					],
					[
						34560,
						2,
						0
					],
					[
						34720,
						3,
						0
					],
					[
						34880,
						1,
						0
					],
					[
						35120,
						2,
						0
					],
					[
						35120,
						3,
						0
					]
				],
				"typeOfSection": 0,
				"gfSection": false,
				"altAnim": false,
				"mustHitSection": true,
				"changeBPM": false,
				"bpm": 125
			},
			{
				"sectionBeats": 4,
				"sectionNotes": [
					[
						37760,
						0,
						0
					],
					[
						37866.6666666667,
						3,
						0
					],
					[
						37520,
						1,
						0
					],
					[
						37760,
						1,
						0
					],
					[
						38160,
						3,
						0
					],
					[
						36560,
						0,
						0
					],
					[
						36560,
						1,
						0
					],
					[
						36800,
						2,
						0
					],
					[
						36920,
						1,
						0
					],
					[
						36800,
						0,
						0
					],
					[
						37160,
						1,
						0
					],
					[
						37280,
						2,
						0
					],
					[
						37280,
						0,
						0
					],
					[
						37520,
						2,
						0
					],
					[
						36560,
						3,
						960,
						"Wall Note"
					],
					[
						38000,
						0,
						600,
						"Wall Note"
					]
				],
				"typeOfSection": 0,
				"gfSection": false,
				"altAnim": false,
				"mustHitSection": true,
				"changeBPM": false,
				"bpm": 125
			},
			{
				"sectionBeats": 4,
				"sectionNotes": [
					[
						39786.6666666667,
						3,
						0
					],
					[
						39200,
						2,
						0
					],
					[
						39440,
						1,
						0
					],
					[
						39680,
						1,
						0
					],
					[
						39920,
						0,
						240,
						"Wall Note"
					],
					[
						39200,
						0,
						0
					],
					[
						40080,
						3,
						0
					],
					[
						40160,
						2,
						0
					],
					[
						38400,
						2,
						0
					],
					[
						38560,
						3,
						0
					],
					[
						38720,
						1,
						0
					],
					[
						38960,
						2,
						0
					],
					[
						38960,
						3,
						0
					]
				],
				"typeOfSection": 0,
				"gfSection": false,
				"altAnim": false,
				"mustHitSection": true,
				"changeBPM": false,
				"bpm": 125
			},
			{
				"sectionBeats": 4,
				"sectionNotes": [
					[
						41600,
						0,
						0
					],
					[
						41706.6666666667,
						3,
						0
					],
					[
						41360,
						1,
						0
					],
					[
						41600,
						1,
						0
					],
					[
						42000,
						3,
						0
					],
					[
						40400,
						0,
						0
					],
					[
						40400,
						1,
						0
					],
					[
						40640,
						2,
						0
					],
					[
						40760,
						1,
						0
					],
					[
						40640,
						0,
						0
					],
					[
						41000,
						1,
						0
					],
					[
						41120,
						2,
						0
					],
					[
						41120,
						0,
						0
					],
					[
						41360,
						2,
						0
					],
					[
						40400,
						3,
						960,
						"Wall Note"
					],
					[
						41840,
						0,
						600,
						"Wall Note"
					]
				],
				"typeOfSection": 0,
				"gfSection": false,
				"altAnim": false,
				"mustHitSection": true,
				"changeBPM": false,
				"bpm": 125
			},
			{
				"sectionBeats": 4,
				"sectionNotes": [
					[
						43626.6666666667,
						3,
						0
					],
					[
						43040,
						2,
						0
					],
					[
						43280,
						1,
						0
					],
					[
						43520,
						1,
						0
					],
					[
						43760,
						0,
						240,
						"Wall Note"
					],
					[
						43040,
						0,
						0
					],
					[
						43920,
						3,
						0
					],
					[
						44000,
						2,
						0
					],
					[
						42240,
						2,
						0
					],
					[
						42400,
						3,
						0
					],
					[
						42560,
						1,
						0
					],
					[
						42800,
						2,
						0
					],
					[
						42800,
						3,
						0
					]
				],
				"typeOfSection": 0,
				"gfSection": false,
				"altAnim": false,
				"mustHitSection": true,
				"changeBPM": false,
				"bpm": 125
			},
			{
				"sectionBeats": 4,
				"sectionNotes": [
					[
						45440,
						0,
						0
					],
					[
						45546.6666666667,
						3,
						0
					],
					[
						45200,
						1,
						0
					],
					[
						45440,
						1,
						0
					],
					[
						45840,
						3,
						0
					],
					[
						44240,
						0,
						0
					],
					[
						44240,
						1,
						0
					],
					[
						44480,
						2,
						0
					],
					[
						44600,
						1,
						0
					],
					[
						44480,
						0,
						0
					],
					[
						44840,
						1,
						0
					],
					[
						44960,
						2,
						0
					],
					[
						44960,
						0,
						0
					],
					[
						45200,
						2,
						0
					],
					[
						44240,
						3,
						960,
						"Wall Note"
					],
					[
						45680,
						0,
						600,
						"Wall Note"
					]
				],
				"typeOfSection": 0,
				"gfSection": false,
				"altAnim": false,
				"mustHitSection": true,
				"changeBPM": false,
				"bpm": 125
			},
			{
				"sectionBeats": 4,
				"sectionNotes": [
					[
						47466.6666666667,
						3,
						0
					],
					[
						46880,
						2,
						0
					],
					[
						47120,
						1,
						0
					],
					[
						47360,
						1,
						0
					],
					[
						47600,
						0,
						240,
						"Wall Note"
					],
					[
						46640,
						1,
						0
					],
					[
						46880,
						0,
						0
					],
					[
						47760,
						3,
						0
					],
					[
						47840,
						2,
						0
					],
					[
						46320,
						3,
						0
					],
					[
						46400,
						1,
						0
					],
					[
						46080,
						2,
						0
					],
					[
						46080,
						3,
						0
					]
				],
				"typeOfSection": 0,
				"gfSection": false,
				"altAnim": false,
				"mustHitSection": true,
				"changeBPM": false,
				"bpm": 125
			},
			{
				"sectionBeats": 4,
				"sectionNotes": [
					[
						49386.6666666667,
						3,
						0
					],
					[
						49280,
						1,
						0
					],
					[
						49680,
						3,
						0
					],
					[
						48080,
						1,
						0
					],
					[
						48440,
						1,
						0
					],
					[
						48320,
						0,
						0
					],
					[
						48680,
						1,
						0
					],
					[
						48800,
						0,
						0
					],
					[
						49040,
						2,
						0
					],
					[
						48080,
						3,
						1080,
						"Wall Note"
					],
					[
						49520,
						0,
						480,
						"Wall Note"
					]
				],
				"typeOfSection": 0,
				"gfSection": false,
				"altAnim": false,
				"mustHitSection": true,
				"changeBPM": false,
				"bpm": 125
			},
			{
				"sectionBeats": 4,
				"sectionNotes": [
					[
						51306.6666666667,
						3,
						0
					],
					[
						50720,
						2,
						0
					],
					[
						50960,
						1,
						0
					],
					[
						51200,
						1,
						0
					],
					[
						51440,
						0,
						240,
						"Wall Note"
					],
					[
						50720,
						0,
						0
					],
					[
						51600,
						3,
						0
					],
					[
						51680,
						2,
						0
					],
					[
						49920,
						2,
						0
					],
					[
						50080,
						3,
						0
					],
					[
						50240,
						1,
						0
					],
					[
						50480,
						2,
						0
					],
					[
						50480,
						3,
						0
					]
				],
				"typeOfSection": 0,
				"gfSection": false,
				"altAnim": false,
				"mustHitSection": true,
				"changeBPM": false,
				"bpm": 125
			},
			{
				"sectionBeats": 4,
				"sectionNotes": [
					[
						53120,
						0,
						0
					],
					[
						53226.6666666667,
						3,
						0
					],
					[
						52880,
						1,
						0
					],
					[
						53120,
						1,
						0
					],
					[
						53520,
						3,
						0
					],
					[
						51920,
						0,
						0
					],
					[
						51920,
						1,
						0
					],
					[
						52160,
						2,
						0
					],
					[
						52280,
						1,
						0
					],
					[
						52160,
						0,
						0
					],
					[
						52520,
						1,
						0
					],
					[
						52640,
						2,
						0
					],
					[
						52640,
						0,
						0
					],
					[
						52880,
						2,
						0
					],
					[
						51920,
						3,
						960,
						"Wall Note"
					],
					[
						53360,
						0,
						600,
						"Wall Note"
					]
				],
				"typeOfSection": 0,
				"gfSection": false,
				"altAnim": false,
				"mustHitSection": true,
				"changeBPM": false,
				"bpm": 125
			},
			{
				"sectionBeats": 4,
				"sectionNotes": [
					[
						55146.6666666667,
						3,
						0
					],
					[
						54560,
						2,
						0
					],
					[
						54800,
						1,
						0
					],
					[
						55040,
						1,
						0
					],
					[
						55280,
						0,
						240,
						"Wall Note"
					],
					[
						54560,
						0,
						0
					],
					[
						55440,
						3,
						0
					],
					[
						55520,
						2,
						0
					],
					[
						53760,
						2,
						0
					],
					[
						53920,
						3,
						0
					],
					[
						54080,
						1,
						0
					],
					[
						54320,
						2,
						0
					],
					[
						54320,
						3,
						0
					]
				],
				"typeOfSection": 0,
				"gfSection": false,
				"altAnim": false,
				"mustHitSection": true,
				"changeBPM": false,
				"bpm": 125
			},
			{
				"sectionBeats": 4,
				"sectionNotes": [
					[
						56960,
						0,
						0
					],
					[
						57066.6666666667,
						3,
						0
					],
					[
						56720,
						1,
						0
					],
					[
						56960,
						1,
						0
					],
					[
						57360,
						3,
						0
					],
					[
						55760,
						0,
						0
					],
					[
						55760,
						1,
						0
					],
					[
						56000,
						2,
						0
					],
					[
						56120,
						1,
						0
					],
					[
						56000,
						0,
						0
					],
					[
						56360,
						1,
						0
					],
					[
						56480,
						2,
						0
					],
					[
						56480,
						0,
						0
					],
					[
						56720,
						2,
						0
					],
					[
						55760,
						3,
						960,
						"Wall Note"
					],
					[
						57200,
						0,
						600,
						"Wall Note"
					]
				],
				"typeOfSection": 0,
				"gfSection": false,
				"altAnim": false,
				"mustHitSection": true,
				"changeBPM": false,
				"bpm": 125
			},
			{
				"sectionBeats": 4,
				"sectionNotes": [
					[
						58986.6666666667,
						3,
						0
					],
					[
						58400,
						2,
						0
					],
					[
						58640,
						1,
						0
					],
					[
						58880,
						1,
						0
					],
					[
						59120,
						0,
						240,
						"Wall Note"
					],
					[
						58400,
						0,
						0
					],
					[
						59280,
						3,
						0
					],
					[
						59360,
						2,
						0
					],
					[
						57600,
						2,
						0
					],
					[
						57760,
						3,
						0
					],
					[
						57920,
						1,
						0
					],
					[
						58160,
						2,
						0
					],
					[
						58160,
						3,
						0
					]
				],
				"typeOfSection": 0,
				"gfSection": false,
				"altAnim": false,
				"mustHitSection": true,
				"changeBPM": false,
				"bpm": 125
			},
			{
				"sectionBeats": 4,
				"sectionNotes": [
					[
						60800,
						0,
						0
					],
					[
						60906.6666666667,
						3,
						0
					],
					[
						60560,
						1,
						0
					],
					[
						60800,
						1,
						0
					],
					[
						61200,
						3,
						0
					],
					[
						59600,
						0,
						0
					],
					[
						59600,
						1,
						0
					],
					[
						59840,
						2,
						0
					],
					[
						59960,
						1,
						0
					],
					[
						59840,
						0,
						0
					],
					[
						60200,
						1,
						0
					],
					[
						60320,
						2,
						0
					],
					[
						60320,
						0,
						0
					],
					[
						60560,
						2,
						0
					],
					[
						59600,
						3,
						960,
						"Wall Note"
					],
					[
						61040,
						0,
						600,
						"Wall Note"
					]
				],
				"typeOfSection": 0,
				"gfSection": false,
				"altAnim": false,
				"mustHitSection": true,
				"changeBPM": false,
				"bpm": 125
			},
			{
				"sectionBeats": 4,
				"sectionNotes": [
					[
						61680,
						3,
						0
					],
					[
						61760,
						1,
						0
					],
					[
						61440,
						2,
						0
					],
					[
						61440,
						3,
						0
					],
					[
						62000,
						1,
						1200
					],
					[
						62000,
						3,
						0
					]
				],
				"typeOfSection": 0,
				"gfSection": false,
				"altAnim": false,
				"mustHitSection": true,
				"changeBPM": false,
				"bpm": 125
			},
			{
				"sectionBeats": 4,
				"sectionNotes": [
					[
						64160,
						2,
						1560
					],
					[
						64160,
						1,
						1560
					]
				],
				"typeOfSection": 0,
				"gfSection": false,
				"altAnim": false,
				"mustHitSection": true,
				"changeBPM": false,
				"bpm": 125
			},
			{
				"sectionBeats": 4,
				"sectionNotes": [
					[
						65920,
						1,
						0
					],
					[
						65920,
						0,
						1800
					],
					[
						66320,
						3,
						720,
						"Wall Note"
					],
					[
						66560,
						2,
						840,
						"Wall Note"
					],
					[
						66720,
						1,
						960,
						"Wall Note"
					]
				],
				"typeOfSection": 0,
				"gfSection": false,
				"altAnim": false,
				"mustHitSection": true,
				"changeBPM": false,
				"bpm": 125
			},
			{
				"sectionBeats": 4,
				"sectionNotes": [
					[
						68640,
						3,
						840
					],
					[
						67920,
						2,
						1560
					]
				],
				"typeOfSection": 0,
				"gfSection": false,
				"altAnim": false,
				"mustHitSection": true,
				"changeBPM": false,
				"bpm": 125
			},
			{
				"sectionBeats": 4,
				"sectionNotes": [
					[
						69680,
						1,
						0
					],
					[
						69680,
						0,
						2040
					],
					[
						70080,
						3,
						720,
						"Wall Note"
					],
					[
						70400,
						2,
						960,
						"Wall Note"
					],
					[
						70800,
						1,
						840,
						"Wall Note"
					]
				],
				"typeOfSection": 0,
				"gfSection": false,
				"altAnim": false,
				"mustHitSection": true,
				"changeBPM": false,
				"bpm": 125
			},
			{
				"sectionBeats": 4,
				"sectionNotes": [
					[
						71840,
						2,
						1560
					],
					[
						71840,
						1,
						1560
					]
				],
				"typeOfSection": 0,
				"gfSection": false,
				"altAnim": false,
				"mustHitSection": true,
				"changeBPM": false,
				"bpm": 125
			},
			{
				"sectionBeats": 4,
				"sectionNotes": [
					[
						73600,
						1,
						0
					],
					[
						73600,
						0,
						1800
					],
					[
						74320,
						1,
						1080,
						"Wall Note"
					],
					[
						74080,
						2,
						840,
						"Wall Note"
					],
					[
						73840,
						3,
						840,
						"Wall Note"
					]
				],
				"typeOfSection": 0,
				"gfSection": false,
				"altAnim": false,
				"mustHitSection": true,
				"changeBPM": false,
				"bpm": 125
			},
			{
				"sectionBeats": 4,
				"sectionNotes": [
					[
						76320,
						3,
						840
					],
					[
						75600,
						2,
						1560
					]
				],
				"typeOfSection": 0,
				"gfSection": false,
				"altAnim": false,
				"mustHitSection": true,
				"changeBPM": false,
				"bpm": 125
			},
			{
				"sectionBeats": 4,
				"sectionNotes": [
					[
						77360,
						2,
						0
					],
					[
						77360,
						0,
						0
					],
					[
						77840,
						2,
						0
					],
					[
						78400,
						1,
						0
					],
					[
						78160,
						2,
						0
					],
					[
						78680,
						1,
						0
					],
					[
						77120,
						1,
						0,
						"Bomb Note"
					],
					[
						77600,
						0,
						0,
						"Bomb Note"
					],
					[
						77600,
						1,
						0,
						"Bomb Note"
					],
					[
						77600,
						2,
						0,
						"Bomb Note"
					]
				],
				"typeOfSection": 0,
				"gfSection": false,
				"altAnim": false,
				"mustHitSection": true,
				"changeBPM": false,
				"bpm": 125
			},
			{
				"sectionBeats": 4,
				"sectionNotes": [
					[
						78800,
						3,
						0
					],
					[
						78800,
						2,
						0
					],
					[
						79280,
						1,
						0
					],
					[
						79760,
						1,
						0
					],
					[
						80080,
						2,
						0
					],
					[
						80480,
						2,
						0
					],
					[
						79520,
						1,
						0,
						"Bomb Note"
					],
					[
						79520,
						2,
						0,
						"Bomb Note"
					],
					[
						79520,
						3,
						0,
						"Bomb Note"
					],
					[
						79040,
						1,
						0,
						"Bomb Note"
					],
					[
						79040,
						0,
						0,
						"Bomb Note"
					],
					[
						79280,
						0,
						0
					]
				],
				"typeOfSection": 0,
				"gfSection": false,
				"altAnim": false,
				"mustHitSection": true,
				"changeBPM": false,
				"bpm": 125
			},
			{
				"sectionBeats": 4,
				"sectionNotes": [
					[
						80720,
						1,
						0
					],
					[
						80720,
						3,
						0
					],
					[
						80960,
						2,
						0
					],
					[
						81200,
						2,
						0
					],
					[
						81200,
						0,
						0
					],
					[
						81680,
						2,
						0
					],
					[
						82240,
						1,
						0
					],
					[
						82520,
						1,
						0
					],
					[
						81440,
						1,
						0,
						"Bomb Note"
					],
					[
						81440,
						0,
						0,
						"Bomb Note"
					],
					[
						81440,
						2,
						0,
						"Bomb Note"
					],
					[
						82000,
						1,
						0
					]
				],
				"typeOfSection": 0,
				"gfSection": false,
				"altAnim": false,
				"mustHitSection": true,
				"changeBPM": false,
				"bpm": 125
			},
			{
				"sectionBeats": 4,
				"sectionNotes": [
					[
						82640,
						3,
						0
					],
					[
						82640,
						2,
						0
					],
					[
						83120,
						2,
						0
					],
					[
						83120,
						0,
						0
					],
					[
						83920,
						2,
						0
					],
					[
						83600,
						0,
						0
					],
					[
						84320,
						0,
						0
					],
					[
						82880,
						3,
						0,
						"Bomb Note"
					],
					[
						82880,
						0,
						0,
						"Bomb Note"
					],
					[
						83360,
						2,
						0,
						"Bomb Note"
					],
					[
						83360,
						3,
						0,
						"Bomb Note"
					],
					[
						83360,
						1,
						0,
						"Bomb Note"
					],
					[
						84160,
						3,
						0,
						"Bomb Note"
					],
					[
						84160,
						1,
						0,
						"Bomb Note"
					]
				],
				"typeOfSection": 0,
				"gfSection": false,
				"altAnim": false,
				"mustHitSection": true,
				"changeBPM": false,
				"bpm": 125
			},
			{
				"sectionBeats": 4,
				"sectionNotes": [
					[
						84560,
						1,
						0
					],
					[
						84560,
						3,
						0
					],
					[
						84800,
						2,
						0
					],
					[
						85040,
						0,
						0
					],
					[
						85520,
						2,
						0
					],
					[
						85840,
						2,
						0
					],
					[
						86080,
						0,
						0
					],
					[
						85160,
						1,
						0
					],
					[
						85280,
						0,
						0
					],
					[
						85400,
						1,
						0
					],
					[
						85640,
						1,
						0
					],
					[
						85720,
						3,
						0
					],
					[
						85960,
						3,
						0
					],
					[
						86200,
						3,
						0
					],
					[
						86320,
						1,
						0
					]
				],
				"typeOfSection": 0,
				"gfSection": false,
				"altAnim": false,
				"mustHitSection": true,
				"changeBPM": false,
				"bpm": 125
			},
			{
				"sectionBeats": 4,
				"sectionNotes": [
					[
						86480,
						3,
						0
					],
					[
						86480,
						2,
						0
					],
					[
						86960,
						0,
						0
					],
					[
						87760,
						2,
						0
					],
					[
						87440,
						0,
						0
					],
					[
						88160,
						2,
						0
					],
					[
						88160,
						0,
						0
					],
					[
						87080,
						3,
						0
					],
					[
						87200,
						2,
						0
					],
					[
						87320,
						1,
						0
					],
					[
						87640,
						0,
						0
					],
					[
						86720,
						0,
						0,
						"Bomb Note"
					],
					[
						86720,
						1,
						0,
						"Bomb Note"
					],
					[
						86720,
						3,
						0,
						"Bomb Note"
					],
					[
						86720,
						2,
						0,
						"Bomb Note"
					],
					[
						88000,
						1,
						0,
						"Bomb Note"
					],
					[
						88000,
						3,
						0,
						"Bomb Note"
					],
					[
						87560,
						2,
						0
					]
				],
				"typeOfSection": 0,
				"gfSection": false,
				"altAnim": false,
				"mustHitSection": true,
				"changeBPM": false,
				"bpm": 125
			},
			{
				"sectionBeats": 4,
				"sectionNotes": [
					[
						88640,
						1,
						0
					],
					[
						88400,
						1,
						0
					],
					[
						88400,
						3,
						0
					],
					[
						88640,
						2,
						0
					],
					[
						88880,
						2,
						0
					],
					[
						88880,
						0,
						0
					],
					[
						89120,
						2,
						0
					],
					[
						89000,
						1,
						0
					],
					[
						89240,
						1,
						0
					],
					[
						89360,
						2,
						0
					],
					[
						89480,
						1,
						0
					],
					[
						89600,
						2,
						0
					],
					[
						89720,
						1,
						0
					],
					[
						89840,
						2,
						0
					],
					[
						89960,
						1,
						0
					],
					[
						90080,
						2,
						0
					],
					[
						90200,
						1,
						0
					]
				],
				"typeOfSection": 0,
				"gfSection": false,
				"altAnim": false,
				"mustHitSection": true,
				"changeBPM": false,
				"bpm": 125
			},
			{
				"sectionBeats": 4,
				"sectionNotes": [
					[
						90320,
						2,
						0
					],
					[
						90440,
						1,
						0
					],
					[
						90560,
						2,
						0
					],
					[
						90680,
						1,
						0
					],
					[
						90840,
						1,
						0
					],
					[
						91120,
						1,
						0
					],
					[
						91280,
						0,
						0
					],
					[
						91520,
						1,
						0
					],
					[
						91280,
						2,
						0
					],
					[
						91760,
						1,
						0
					],
					[
						91760,
						3,
						0
					],
					[
						92080,
						1,
						0
					],
					[
						91040,
						2,
						0
					],
					[
						91600,
						2,
						0
					],
					[
						92000,
						2,
						0
					]
				],
				"typeOfSection": 0,
				"gfSection": false,
				"altAnim": false,
				"mustHitSection": true,
				"changeBPM": false,
				"bpm": 125
			},
			{
				"sectionBeats": 4,
				"sectionNotes": [
					[
						92240,
						2,
						0
					],
					[
						92240,
						0,
						360
					],
					[
						93546.6666666667,
						3,
						0
					],
					[
						92960,
						2,
						0
					],
					[
						93200,
						1,
						0
					],
					[
						93440,
						1,
						0
					],
					[
						92480,
						1,
						0,
						"Bomb Note"
					],
					[
						92480,
						2,
						0,
						"Bomb Note"
					],
					[
						93680,
						0,
						240,
						"Wall Note"
					],
					[
						92720,
						1,
						0
					],
					[
						92960,
						0,
						0
					],
					[
						93840,
						3,
						0
					],
					[
						93920,
						2,
						0
					]
				],
				"typeOfSection": 0,
				"gfSection": false,
				"altAnim": false,
				"mustHitSection": true,
				"changeBPM": false,
				"bpm": 125
			},
			{
				"sectionBeats": 4,
				"sectionNotes": [
					[
						95466.6666666667,
						3,
						0
					],
					[
						95360,
						1,
						0
					],
					[
						95760,
						3,
						0
					],
					[
						94160,
						1,
						0
					],
					[
						94520,
						1,
						0
					],
					[
						94400,
						0,
						0
					],
					[
						94760,
						1,
						0
					],
					[
						94880,
						0,
						0
					],
					[
						95120,
						2,
						0
					],
					[
						94160,
						3,
						1080,
						"Wall Note"
					],
					[
						95600,
						0,
						480,
						"Wall Note"
					]
				],
				"typeOfSection": 0,
				"gfSection": false,
				"altAnim": false,
				"mustHitSection": true,
				"changeBPM": false,
				"bpm": 125
			},
			{
				"sectionBeats": 4,
				"sectionNotes": [
					[
						97386.6666666667,
						3,
						0
					],
					[
						96800,
						2,
						0
					],
					[
						97040,
						1,
						0
					],
					[
						97280,
						1,
						0
					],
					[
						97520,
						0,
						240,
						"Wall Note"
					],
					[
						96800,
						0,
						0
					],
					[
						97680,
						3,
						0
					],
					[
						97760,
						2,
						0
					],
					[
						96000,
						2,
						0
					],
					[
						96160,
						3,
						0
					],
					[
						96320,
						1,
						0
					],
					[
						96560,
						2,
						0
					],
					[
						96560,
						3,
						0
					]
				],
				"typeOfSection": 0,
				"gfSection": false,
				"altAnim": false,
				"mustHitSection": true,
				"changeBPM": false,
				"bpm": 125
			},
			{
				"sectionBeats": 4,
				"sectionNotes": [
					[
						99200,
						0,
						0
					],
					[
						99306.6666666667,
						3,
						0
					],
					[
						98960,
						1,
						0
					],
					[
						99200,
						1,
						0
					],
					[
						99600,
						3,
						0
					],
					[
						98000,
						0,
						0
					],
					[
						98000,
						1,
						0
					],
					[
						98240,
						2,
						0
					],
					[
						98360,
						1,
						0
					],
					[
						98240,
						0,
						0
					],
					[
						98600,
						1,
						0
					],
					[
						98720,
						2,
						0
					],
					[
						98720,
						0,
						0
					],
					[
						98960,
						2,
						0
					],
					[
						98000,
						3,
						960,
						"Wall Note"
					],
					[
						99440,
						0,
						600,
						"Wall Note"
					]
				],
				"typeOfSection": 0,
				"gfSection": false,
				"altAnim": false,
				"mustHitSection": true,
				"changeBPM": false,
				"bpm": 125
			},
			{
				"sectionBeats": 4,
				"sectionNotes": [
					[
						101226.666666667,
						3,
						0
					],
					[
						100640,
						2,
						0
					],
					[
						100880,
						1,
						0
					],
					[
						101120,
						1,
						0
					],
					[
						101360,
						0,
						240,
						"Wall Note"
					],
					[
						100640,
						0,
						0
					],
					[
						101520,
						3,
						0
					],
					[
						101600,
						2,
						0
					],
					[
						99840,
						2,
						0
					],
					[
						100000,
						3,
						0
					],
					[
						100160,
						1,
						0
					],
					[
						100400,
						2,
						0
					],
					[
						100400,
						3,
						0
					]
				],
				"typeOfSection": 0,
				"gfSection": false,
				"altAnim": false,
				"mustHitSection": true,
				"changeBPM": false,
				"bpm": 125
			},
			{
				"sectionBeats": 4,
				"sectionNotes": [
					[
						103040,
						0,
						0
					],
					[
						103146.666666667,
						3,
						0
					],
					[
						102800,
						1,
						0
					],
					[
						103040,
						1,
						0
					],
					[
						103440,
						3,
						0
					],
					[
						101840,
						0,
						0
					],
					[
						101840,
						1,
						0
					],
					[
						102080,
						2,
						0
					],
					[
						102200,
						1,
						0
					],
					[
						102080,
						0,
						0
					],
					[
						102440,
						1,
						0
					],
					[
						102560,
						2,
						0
					],
					[
						102560,
						0,
						0
					],
					[
						102800,
						2,
						0
					],
					[
						101840,
						3,
						960,
						"Wall Note"
					],
					[
						103280,
						0,
						600,
						"Wall Note"
					]
				],
				"typeOfSection": 0,
				"gfSection": false,
				"altAnim": false,
				"mustHitSection": true,
				"changeBPM": false,
				"bpm": 125
			},
			{
				"sectionBeats": 4,
				"sectionNotes": [
					[
						105066.666666667,
						3,
						0
					],
					[
						104480,
						2,
						0
					],
					[
						104720,
						1,
						0
					],
					[
						104960,
						1,
						0
					],
					[
						105200,
						0,
						240,
						"Wall Note"
					],
					[
						104480,
						0,
						0
					],
					[
						105360,
						3,
						0
					],
					[
						105440,
						2,
						0
					],
					[
						103680,
						2,
						0
					],
					[
						103840,
						3,
						0
					],
					[
						104000,
						1,
						0
					],
					[
						104240,
						2,
						0
					],
					[
						104240,
						3,
						0
					]
				],
				"typeOfSection": 0,
				"gfSection": false,
				"altAnim": false,
				"mustHitSection": true,
				"changeBPM": false,
				"bpm": 125
			},
			{
				"sectionBeats": 4,
				"sectionNotes": [
					[
						106880,
						0,
						0
					],
					[
						106986.666666667,
						3,
						0
					],
					[
						106640,
						1,
						0
					],
					[
						106880,
						1,
						0
					],
					[
						107280,
						3,
						0
					],
					[
						105680,
						0,
						0
					],
					[
						105680,
						1,
						0
					],
					[
						105920,
						2,
						0
					],
					[
						106040,
						1,
						0
					],
					[
						105920,
						0,
						0
					],
					[
						106280,
						1,
						0
					],
					[
						106400,
						2,
						0
					],
					[
						106400,
						0,
						0
					],
					[
						106640,
						2,
						0
					],
					[
						105680,
						3,
						960,
						"Wall Note"
					],
					[
						107120,
						0,
						600,
						"Wall Note"
					]
				],
				"typeOfSection": 0,
				"gfSection": false,
				"altAnim": false,
				"mustHitSection": true,
				"changeBPM": false,
				"bpm": 125
			},
			{
				"sectionBeats": 4,
				"sectionNotes": [
					[
						108906.666666667,
						3,
						0
					],
					[
						108320,
						2,
						0
					],
					[
						108560,
						1,
						0
					],
					[
						108800,
						1,
						0
					],
					[
						109040,
						0,
						240,
						"Wall Note"
					],
					[
						108080,
						1,
						0
					],
					[
						108320,
						0,
						0
					],
					[
						109200,
						3,
						0
					],
					[
						109280,
						2,
						0
					],
					[
						107760,
						3,
						0
					],
					[
						107840,
						1,
						0
					],
					[
						107520,
						2,
						0
					],
					[
						107520,
						3,
						0
					]
				],
				"typeOfSection": 0,
				"gfSection": false,
				"altAnim": false,
				"mustHitSection": true,
				"changeBPM": false,
				"bpm": 125
			},
			{
				"sectionBeats": 4,
				"sectionNotes": [
					[
						110826.666666667,
						3,
						0
					],
					[
						110720,
						1,
						0
					],
					[
						111120,
						3,
						0
					],
					[
						109520,
						1,
						0
					],
					[
						109880,
						1,
						0
					],
					[
						109760,
						0,
						0
					],
					[
						110120,
						1,
						0
					],
					[
						110240,
						0,
						0
					],
					[
						110480,
						2,
						0
					],
					[
						109520,
						3,
						1080,
						"Wall Note"
					],
					[
						110960,
						0,
						480,
						"Wall Note"
					]
				],
				"typeOfSection": 0,
				"gfSection": false,
				"altAnim": false,
				"mustHitSection": true,
				"changeBPM": false,
				"bpm": 125
			},
			{
				"sectionBeats": 4,
				"sectionNotes": [
					[
						112746.666666667,
						3,
						0
					],
					[
						112160,
						2,
						0
					],
					[
						112400,
						1,
						0
					],
					[
						112640,
						1,
						0
					],
					[
						112880,
						0,
						240,
						"Wall Note"
					],
					[
						112160,
						0,
						0
					],
					[
						113040,
						3,
						0
					],
					[
						113120,
						2,
						0
					],
					[
						111360,
						2,
						0
					],
					[
						111520,
						3,
						0
					],
					[
						111680,
						1,
						0
					],
					[
						111920,
						2,
						0
					],
					[
						111920,
						3,
						0
					]
				],
				"typeOfSection": 0,
				"gfSection": false,
				"altAnim": false,
				"mustHitSection": true,
				"changeBPM": false,
				"bpm": 125
			},
			{
				"sectionBeats": 4,
				"sectionNotes": [
					[
						114560,
						0,
						0
					],
					[
						114666.666666667,
						3,
						0
					],
					[
						114320,
						1,
						0
					],
					[
						114560,
						1,
						0
					],
					[
						114960,
						3,
						0
					],
					[
						113360,
						0,
						0
					],
					[
						113360,
						1,
						0
					],
					[
						113600,
						2,
						0
					],
					[
						113720,
						1,
						0
					],
					[
						113600,
						0,
						0
					],
					[
						113960,
						1,
						0
					],
					[
						114080,
						2,
						0
					],
					[
						114080,
						0,
						0
					],
					[
						114320,
						2,
						0
					],
					[
						113360,
						3,
						960,
						"Wall Note"
					],
					[
						114800,
						0,
						600,
						"Wall Note"
					]
				],
				"typeOfSection": 0,
				"gfSection": false,
				"altAnim": false,
				"mustHitSection": true,
				"changeBPM": false,
				"bpm": 125
			},
			{
				"sectionBeats": 4,
				"sectionNotes": [
					[
						116586.666666667,
						3,
						0
					],
					[
						116000,
						2,
						0
					],
					[
						116240,
						1,
						0
					],
					[
						116480,
						1,
						0
					],
					[
						116720,
						0,
						240,
						"Wall Note"
					],
					[
						116000,
						0,
						0
					],
					[
						116880,
						3,
						0
					],
					[
						116960,
						2,
						0
					],
					[
						115200,
						2,
						0
					],
					[
						115360,
						3,
						0
					],
					[
						115520,
						1,
						0
					],
					[
						115760,
						2,
						0
					],
					[
						115760,
						3,
						0
					]
				],
				"typeOfSection": 0,
				"gfSection": false,
				"altAnim": false,
				"mustHitSection": true,
				"changeBPM": false,
				"bpm": 125
			},
			{
				"sectionBeats": 4,
				"sectionNotes": [
					[
						118400,
						0,
						0
					],
					[
						118506.666666667,
						3,
						0
					],
					[
						118160,
						1,
						0
					],
					[
						118400,
						1,
						0
					],
					[
						118800,
						3,
						0
					],
					[
						117200,
						0,
						0
					],
					[
						117200,
						1,
						0
					],
					[
						117440,
						2,
						0
					],
					[
						117560,
						1,
						0
					],
					[
						117440,
						0,
						0
					],
					[
						117800,
						1,
						0
					],
					[
						117920,
						2,
						0
					],
					[
						117920,
						0,
						0
					],
					[
						118160,
						2,
						0
					],
					[
						117200,
						3,
						960,
						"Wall Note"
					],
					[
						118640,
						0,
						600,
						"Wall Note"
					]
				],
				"typeOfSection": 0,
				"gfSection": false,
				"altAnim": false,
				"mustHitSection": true,
				"changeBPM": false,
				"bpm": 125
			},
			{
				"sectionBeats": 4,
				"sectionNotes": [
					[
						120426.666666667,
						3,
						0
					],
					[
						119840,
						2,
						0
					],
					[
						120080,
						1,
						0
					],
					[
						120320,
						1,
						0
					],
					[
						120560,
						0,
						240,
						"Wall Note"
					],
					[
						119840,
						0,
						0
					],
					[
						120720,
						3,
						0
					],
					[
						120800,
						2,
						0
					],
					[
						119040,
						2,
						0
					],
					[
						119200,
						3,
						0
					],
					[
						119360,
						1,
						0
					],
					[
						119600,
						2,
						0
					],
					[
						119600,
						3,
						0
					]
				],
				"typeOfSection": 0,
				"gfSection": false,
				"altAnim": false,
				"mustHitSection": true,
				"changeBPM": false,
				"bpm": 125
			},
			{
				"sectionBeats": 4,
				"sectionNotes": [
					[
						122240,
						0,
						0
					],
					[
						122346.666666667,
						3,
						0
					],
					[
						122000,
						1,
						0
					],
					[
						122240,
						1,
						0
					],
					[
						122640,
						3,
						0
					],
					[
						121040,
						0,
						0
					],
					[
						121040,
						1,
						0
					],
					[
						121280,
						2,
						0
					],
					[
						121400,
						1,
						0
					],
					[
						121280,
						0,
						0
					],
					[
						121640,
						1,
						0
					],
					[
						121760,
						2,
						0
					],
					[
						121760,
						0,
						0
					],
					[
						122000,
						2,
						0
					],
					[
						121040,
						3,
						960,
						"Wall Note"
					],
					[
						122480,
						0,
						600,
						"Wall Note"
					]
				],
				"typeOfSection": 0,
				"gfSection": false,
				"altAnim": false,
				"mustHitSection": true,
				"changeBPM": false,
				"bpm": 125
			},
			{
				"sectionBeats": 4,
				"sectionNotes": [
					[
						123120,
						3,
						0
					],
					[
						123200,
						1,
						0
					],
					[
						122880,
						2,
						0
					],
					[
						122880,
						3,
						0
					],
					[
						123440,
						3,
						0
					],
					[
						123440,
						1,
						240
					],
					[
						123920,
						0,
						360
					],
					[
						123920,
						2,
						0
					],
					[
						124400,
						1,
						0
					],
					[
						124400,
						2,
						240
					]
				],
				"typeOfSection": 0,
				"gfSection": false,
				"altAnim": false,
				"mustHitSection": true,
				"changeBPM": false,
				"bpm": 125
			},
			{
				"sectionBeats": 4,
				"sectionNotes": [
					[
						124880,
						1,
						0
					],
					[
						124880,
						3,
						0
					],
					[
						125360,
						0,
						0
					],
					[
						125360,
						1,
						0
					],
					[
						126080,
						2,
						0
					],
					[
						126080,
						3,
						0
					],
					[
						126320,
						1,
						0
					],
					[
						126320,
						3,
						0
					],
					[
						126560,
						0,
						0
					],
					[
						126560,
						3,
						0
					]
				],
				"typeOfSection": 0,
				"gfSection": false,
				"altAnim": false,
				"mustHitSection": true,
				"changeBPM": false,
				"bpm": 125
			},
			{
				"sectionBeats": 4,
				"sectionNotes": [
					[
						126800,
						3,
						0
					],
					[
						126800,
						1,
						0
					],
					[
						127280,
						2,
						0
					],
					[
						127280,
						1,
						0
					],
					[
						127760,
						1,
						0
					],
					[
						127760,
						2,
						360
					],
					[
						128240,
						3,
						480
					],
					[
						128240,
						2,
						0
					],
					[
						127280,
						0,
						360
					]
				],
				"typeOfSection": 0,
				"gfSection": false,
				"altAnim": false,
				"mustHitSection": true,
				"changeBPM": false,
				"bpm": 125
			},
			{
				"sectionBeats": 4,
				"sectionNotes": [
					[
						128720,
						1,
						0
					],
					[
						129200,
						0,
						0
					],
					[
						129200,
						1,
						0
					],
					[
						129920,
						2,
						0
					],
					[
						129920,
						3,
						0
					],
					[
						130160,
						1,
						0
					],
					[
						130160,
						3,
						0
					],
					[
						130400,
						0,
						0
					],
					[
						130400,
						3,
						0
					],
					[
						128720,
						2,
						0
					]
				],
				"typeOfSection": 0,
				"gfSection": false,
				"altAnim": false,
				"mustHitSection": true,
				"changeBPM": false,
				"bpm": 125
			},
			{
				"sectionBeats": 4,
				"sectionNotes": [
					[
						130640,
						3,
						0
					],
					[
						130640,
						1,
						0
					],
					[
						131120,
						2,
						0
					],
					[
						131120,
						1,
						0
					],
					[
						131600,
						1,
						0
					],
					[
						131600,
						2,
						360
					],
					[
						132080,
						3,
						480
					],
					[
						132080,
						2,
						0
					],
					[
						131120,
						0,
						360
					]
				],
				"typeOfSection": 0,
				"gfSection": false,
				"altAnim": false,
				"mustHitSection": true,
				"changeBPM": false,
				"bpm": 125
			},
			{
				"sectionBeats": 4,
				"sectionNotes": [
					[
						132560,
						1,
						0
					],
					[
						133040,
						0,
						0
					],
					[
						133040,
						1,
						0
					],
					[
						133760,
						2,
						0
					],
					[
						133760,
						3,
						0
					],
					[
						134000,
						1,
						0
					],
					[
						134000,
						3,
						0
					],
					[
						134240,
						0,
						0
					],
					[
						134240,
						3,
						0
					],
					[
						132560,
						2,
						0
					]
				],
				"typeOfSection": 0,
				"gfSection": false,
				"altAnim": false,
				"mustHitSection": true,
				"changeBPM": false,
				"bpm": 125
			},
			{
				"sectionBeats": 4,
				"sectionNotes": [
					[
						134480,
						3,
						0
					],
					[
						134480,
						1,
						0
					],
					[
						134960,
						2,
						0
					],
					[
						134960,
						1,
						0
					],
					[
						135440,
						1,
						0
					],
					[
						135440,
						2,
						360
					],
					[
						135920,
						3,
						480
					],
					[
						135920,
						2,
						0
					],
					[
						134960,
						0,
						360
					]
				],
				"typeOfSection": 0,
				"gfSection": false,
				"altAnim": false,
				"mustHitSection": true,
				"changeBPM": false,
				"bpm": 125
			},
			{
				"sectionBeats": 4,
				"sectionNotes": [
					[
						136400,
						2,
						0
					],
					[
						136880,
						3,
						0
					],
					[
						136880,
						2,
						0
					],
					[
						137600,
						1,
						0
					],
					[
						137600,
						0,
						0
					],
					[
						137840,
						2,
						0
					],
					[
						137840,
						0,
						0
					],
					[
						138080,
						3,
						0
					],
					[
						138080,
						0,
						0
					],
					[
						136400,
						1,
						0
					]
				],
				"typeOfSection": 0,
				"gfSection": false,
				"altAnim": false,
				"mustHitSection": true,
				"changeBPM": false,
				"bpm": 125
			},
			{
				"sectionBeats": 4,
				"sectionNotes": [
					[
						138320,
						0,
						0
					],
					[
						138320,
						2,
						0
					],
					[
						138800,
						0,
						1080
					],
					[
						138800,
						3,
						1080
					]
				],
				"typeOfSection": 0,
				"gfSection": false,
				"altAnim": false,
				"mustHitSection": true,
				"changeBPM": false,
				"bpm": 125
			},
			{
				"sectionBeats": 4,
				"sectionNotes": [],
				"typeOfSection": 0,
				"gfSection": false,
				"altAnim": false,
				"mustHitSection": true,
				"changeBPM": false,
				"bpm": 125
			},
			{
				"sectionBeats": 4,
				"sectionNotes": [],
				"typeOfSection": 0,
				"gfSection": false,
				"altAnim": false,
				"mustHitSection": true,
				"changeBPM": false,
				"bpm": 125
			},
			{
				"sectionBeats": 4,
				"sectionNotes": [],
				"typeOfSection": 0,
				"gfSection": false,
				"altAnim": false,
				"mustHitSection": true,
				"changeBPM": false,
				"bpm": 125
			},
			{
				"sectionBeats": 4,
				"sectionNotes": [],
				"typeOfSection": 0,
				"gfSection": false,
				"altAnim": false,
				"mustHitSection": true,
				"changeBPM": false,
				"bpm": 125
			},
			{
				"sectionBeats": 4,
				"sectionNotes": [],
				"typeOfSection": 0,
				"gfSection": false,
				"altAnim": false,
				"mustHitSection": true,
				"changeBPM": false,
				"bpm": 125
			},
			{
				"sectionBeats": 4,
				"sectionNotes": [],
				"typeOfSection": 0,
				"gfSection": false,
				"altAnim": false,
				"mustHitSection": true,
				"changeBPM": false,
				"bpm": 125
			},
			{
				"sectionBeats": 4,
				"sectionNotes": [],
				"typeOfSection": 0,
				"gfSection": false,
				"altAnim": false,
				"mustHitSection": true,
				"changeBPM": false,
				"bpm": 125
			},
			{
				"gfSection": false,
				"altAnim": false,
				"typeOfSection": 0,
				"sectionNotes": [],
				"bpm": 125,
				"sectionBeats": 4,
				"changeBPM": false,
				"mustHitSection": true
			}
		],
		"player2": "transparent",
		"disableAntiMash": false,
		"splashSkin": "noteSplashes",
		"songInstVolume": 1,
		"song": "Crab Rave",
		"disableDebugButtons": false,
		"arrowSkin": "",
		"validScore": true,
		"characterTrails": false,
		"speed": 3,
		"swapStrumLines": false,
		"events": [],
		"gfVersion": "transparent",
		"healthdrainKill": false,
		"cameraMoveOnNotes": false,
		"healthdrain": 0,
		"stage": "crab rave",
		"needsVoices": false,
		"bpm": 125
	}
}